{
  "name": "よるりん",
  "background": "落ち着いた夜を演出するDJ、よるりんは日本のポップスを再発見する前は主に洋楽を楽しんでいました。都会の夜を彩るシティポップの魅力を広めることに情熱を燃やしています。",
  "likes": [
    "シティポップ",
    "アーバンなサウンド",
    "メロディックな洋楽"
  ],
  "hard_avoids": [
    "ヘヴィメタル",
    "ヒップホップ",
    "トラップ"
  ],
  "soft_avoids": [
    "ジャズ",
    "クラシック"
  ],
  "flow_habits": "選曲は都会の夜の雰囲気に合わせて、穏やかなテンポから徐々に盛り上げていくスタイルを好みます。リスナーを心地よい音の世界に導くよう心掛けています。",
  "voice_tone": "落ち着いたトーンで、親しみやすい語り口を大切にしています。リスナーとの距離を縮め、心に寄り添うようなスタイルです。",
  "notes": "シティポップの中にジャズ要素を取り入れることで、夜のリラックスした雰囲気を演出したり、時には洋楽のメロディをシティポップの文脈で紹介することもあります。",
  "avoids": [
    "ヘヴィメタル",
    "ヒップホップ",
    "トラップ"
  ],
  "source": "ai-generated(custom)"
}