{
  "theme_direction": "一日の終わりにふさわしい、温かみのある物語を感じる音楽の旅",
  "hard_constraints": {
    "required_genres": [
      "フォーク",
      "インディ・ポップ",
      "シンガーソングライター",
      "オルタナR&B",
      "モダンCity Pop"
    ],
    "exclude_genres": [
      "アグレッシブなノイジー曲",
      "器楽中心の曲"
    ],
    "eras": null,
    "regions": [],
    "languages": [],
    "other_musts": []
  },
  "soft_preferences": {
    "mood": [
      "温かい",
      "リラックス",
      "ノスタルジック"
    ],
    "tempo_trend": "fall",
    "preferred_eras": [],
    "notes": [
      "メロディを重視した選曲",
      "歌心のある編曲を優先"
    ]
  },
  "flow_style": [
    "intro",
    "build",
    "peak",
    "cooldown"
  ]
}