{
  "candidates": [
    {
      "title": "Home",
      "artist": "Edward Sharpe & The Magnetic Zeros",
      "album": "Up From Below",
      "arc": "intro",
      "reason": "心地よいアコースティックギターのリフが印象的で、聴く人を優しく包み込む。",
      "whyPersonaFit": "物語性を感じる歌詞と温かいメロディが、語り口調のスタイルにぴったり。",
      "whyThemeFit": "一日の終わりに聴くと、心がほっこりする温かみのある音楽。",
      "year_guess": 2009
    },
    {
      "title": "Peach",
      "artist": "The Front Bottoms",
      "album": "Talon of the Hawk",
      "arc": "build",
      "reason": "感情豊かなボーカルとストーリー性のある歌詞が、聴く人の心に響く。",
      "whyPersonaFit": "歌心のある編曲が、物語重視のスタイルにマッチ。",
      "whyThemeFit": "ノスタルジックな雰囲気が、一日の終わりにぴったり。",
      "year_guess": 2013
    },
    {
      "title": "Landslide",
      "artist": "Fleetwood Mac",
      "album": "Fleetwood Mac",
      "arc": "peak",
      "reason": "シンプルなアレンジと力強いメロディが、深い感情を引き出す。",
      "whyPersonaFit": "温かいトーンが、語り口調のスタイルに自然に溶け込む。",
      "whyThemeFit": "人生の変化を感じさせる内容が、一日の終わりに共鳴する。",
      "year_guess": 1975
    },
    {
      "title": "Japanese Breakfast",
      "artist": "Boyish",
      "album": null,
      "arc": "cooldown",
      "reason": "穏やかなメロディとリラックスした雰囲気が、心を落ち着ける。",
      "whyPersonaFit": "メロディが際立つアレンジが、好みのスタイルに合致。",
      "whyThemeFit": "温かみのあるサウンドが、日の終わりにリラックスさせる。",
      "year_guess": 2021
    },
    {
      "title": "Dreams",
      "artist": "Fleetwood Mac",
      "album": "Rumours",
      "arc": "cooldown",
      "reason": "エモーショナルなボーカルと美しいメロディが、心を和ませる。",
      "whyPersonaFit": "歌心のある楽曲が、物語重視のスタイルに完璧にフィット。",
      "whyThemeFit": "ノスタルジックでリラックスした雰囲気が、一日の終わりに最適。",
      "year_guess": 1977
    }
  ]
}