{
  "candidates": [
    {
      "title": "Plastic Love",
      "artist": "Mariya Takeuchi",
      "album": "Variety",
      "arc": "other",
      "reason": "シティポップの代表作で、心地よいビートとメロディが特徴。イントロからリスナーを引き込む効果がある。",
      "whyPersonaFit": "よるりんのスタイルにぴったりの名曲で、都会的なセンスを感じさせる。",
      "whyThemeFit": "1980年代のシティポップを象徴する楽曲で、夜の街を歩く感覚を引き立てる。",
      "year_guess": 1984,
      "intended_role": "anchor",
      "popularity_hint": "high",
      "notes_for_scoring": ""
    },
    {
      "title": "Stay With Me",
      "artist": "Miki Matsubara",
      "album": "Pocket Park",
      "arc": "other",
      "reason": "シティポップの名曲で、心地よいメロディが夜の雰囲気にぴったり。",
      "whyPersonaFit": "都会的でおしゃれな雰囲気を持ち、リスナーにときめきを与える。",
      "whyThemeFit": "1980年代のシティポップの代表的なトラックで、高揚感を持たせる要素がある。",
      "year_guess": 1982,
      "intended_role": "anchor",
      "popularity_hint": "high",
      "notes_for_scoring": ""
    },
    {
      "title": "Midnight Pretenders",
      "artist": "Tomoko Aran",
      "album": "Fuyu no Uta",
      "arc": "build",
      "reason": "メロディとリズムが心地よく、徐々に盛り上がる構成が特徴。",
      "whyPersonaFit": "よるりんの選曲スタイルに合い、都会的な感覚を持っている。",
      "whyThemeFit": "夜の街を感じさせるトラックで、シティポップの魅力を引き立てる。",
      "year_guess": 1983,
      "intended_role": "anchor",
      "popularity_hint": "mid",
      "notes_for_scoring": ""
    },
    {
      "title": "Love Talkin'",
      "artist": "Yumi Matsutoya",
      "album": "The 14th Moon",
      "arc": "build",
      "reason": "しっとりとした雰囲気を持ちながらも、リズム感があり、次の曲への橋渡しがスムーズ。",
      "whyPersonaFit": "都会的でおしゃれな雰囲気があり、リスナーに心地よい体験を提供する。",
      "whyThemeFit": "1980年代のシティポップを代表するトラックで、徐々に盛り上がる。",
      "year_guess": 1981,
      "intended_role": "deep",
      "popularity_hint": "mid",
      "notes_for_scoring": ""
    },
    {
      "title": "Sayonara no Natsu",
      "artist": "Yumi Matsutoya",
      "album": "The 14th Moon",
      "arc": "build",
      "reason": "心地よいメロディが特徴で、前の曲からの流れを自然に引き継ぐ。",
      "whyPersonaFit": "よるりんのスタイルに合った、都会的でしっとりした雰囲気を持つ。",
      "whyThemeFit": "シティポップの中でも特に夜の雰囲気を演出できる楽曲。",
      "year_guess": 1980,
      "intended_role": "deep",
      "popularity_hint": "mid",
      "notes_for_scoring": ""
    },
    {
      "title": "Kimi wa Tennen Shounen",
      "artist": "Kiyotaka Sugiyama",
      "album": "Kimi wa Tennen Shounen",
      "arc": "peak",
      "reason": "エネルギッシュなサウンドで、盛り上がりを感じさせる。",
      "whyPersonaFit": "都会的な魅力を持ち、リスナーに高揚感を与える。",
      "whyThemeFit": "シティポップの中でも特に明るいトーンで、夜の街を彩る。",
      "year_guess": 1986,
      "intended_role": "wildcard",
      "popularity_hint": "low",
      "notes_for_scoring": ""
    },
    {
      "title": "Ain't Nobody",
      "artist": "Chaka Khan",
      "album": "I Feel for You",
      "arc": "peak",
      "reason": "ディスコ・ファンクの名曲で、リズム感が強く、盛り上がりを作る。",
      "whyPersonaFit": "都会的でおしゃれな雰囲気を持ち、リスナーに楽しさを提供する。",
      "whyThemeFit": "シティポップの流れの中で、質感が近いトラック。",
      "year_guess": 1983,
      "intended_role": "wildcard",
      "popularity_hint": "high",
      "notes_for_scoring": ""
    },
    {
      "title": "Kaze ni Naru",
      "artist": "Kenshi Yonezu",
      "album": "Bremen",
      "arc": "cooldown",
      "reason": "新鋭アーティストの楽曲で、しっとりとした雰囲気が特徴。",
      "whyPersonaFit": "都会的で新しい感覚を持ち、リスナーにときめきを与える。",
      "whyThemeFit": "現代のシティポップの流れを汲む楽曲で、夜の雰囲気を引き立てる。",
      "year_guess": 2018,
      "intended_role": "deep",
      "popularity_hint": "high",
      "notes_for_scoring": ""
    },
    {
      "title": "Mikan",
      "artist": "Kenshi Yonezu",
      "album": "STRAY SHEEP",
      "arc": "cooldown",
      "reason": "しっとりとしたメロディが特徴で、心地よい余韻を残す。",
      "whyPersonaFit": "都会的な感覚を持ち、リスナーに穏やかな体験を提供する。",
      "whyThemeFit": "現代のシティポップの要素を持ち、夜の雰囲気を引き立てる。",
      "year_guess": 2020,
      "intended_role": "deep",
      "popularity_hint": "high",
      "notes_for_scoring": ""
    },
    {
      "title": "Blue Light Yokohama",
      "artist": "Aki Yashiro",
      "album": "Blue Light Yokohama",
      "arc": "cooldown",
      "reason": "しっとりとしたバラードで、夜の雰囲気を演出する。",
      "whyPersonaFit": "よるりんのスタイルに合った、都会的でしっとりした雰囲気を持つ。",
      "whyThemeFit": "シティポップの中でも特に夜の雰囲気を演出できる楽曲。",
      "year_guess": 1979,
      "intended_role": "deep",
      "popularity_hint": "mid",
      "notes_for_scoring": ""
    },
    {
      "title": "Ue o Muite Arukou",
      "artist": "Kyu Sakamoto",
      "album": "Kyu Sakamoto",
      "arc": "cooldown",
      "reason": "しっとりとしたメロディが特徴で、心地よい雰囲気を持つ。",
      "whyPersonaFit": "都会的でおしゃれな雰囲気を持ち、リスナーに優しい体験を提供する。",
      "whyThemeFit": "シティポップの流れを受け継ぎつつも、独自の魅力がある。",
      "year_guess": 1961,
      "intended_role": "deep",
      "popularity_hint": "high",
      "notes_for_scoring": ""
    },
    {
      "title": "Kimi to Kawaii Anoko no Uta",
      "artist": "Takako Matsu",
      "album": "Takako Matsu",
      "arc": "other",
      "reason": "心地よいメロディとリズムが特徴で、流れを変える役割を果たす。",
      "whyPersonaFit": "よるりんのスタイルに合った、都会的で心地よい雰囲気を持つ。",
      "whyThemeFit": "シティポップの中でも特にリズム感を強調した楽曲。",
      "year_guess": 1984,
      "intended_role": "wildcard",
      "popularity_hint": "mid",
      "notes_for_scoring": ""
    },
    {
      "title": "Blue Moon",
      "artist": "Kiyotaka Sugiyama",
      "album": "Kiyotaka Sugiyama",
      "arc": "other",
      "reason": "しっとりとしたメロディが特徴で、全体の雰囲気を引き締める役割を果たす。",
      "whyPersonaFit": "都会的でおしゃれな雰囲気を持ち、リスナーに穏やかな体験を提供する。",
      "whyThemeFit": "シティポップの流れを受け継ぎつつも、独自の魅力がある。",
      "year_guess": 1985,
      "intended_role": "wildcard",
      "popularity_hint": "low",
      "notes_for_scoring": ""
    }
  ]
}